_langid.cpython-38-darwin.so
langid_pyc/__init__.py
langid_pyc/default.py
langid_pyc/identifier.py
langid_pyc/ldpy3.pmodel
langid_pyc-0.1.0.dist-info/LICENSE
langid_pyc-0.1.0.dist-info/METADATA
langid_pyc-0.1.0.dist-info/WHEEL
langid_pyc-0.1.0.dist-info/top_level.txt
langid_pyc-0.1.0.dist-info/RECORD
