Metadata-Version: 2.1
Name: langid-pyc
Version: 0.1.0
Summary: Written in C drop-in replacement of the language identification tool langid.py
Author-email: Aleksandr Lukoianov <liablefish@gmail.com>
License: langid.pyc - Language Identifier
Project-URL: Homepage, https://github.com/LiableFish/langid.pyc
Keywords: language detection,language identification,langid,langid.py
Classifier: Programming Language :: Python :: 3
Classifier: Development Status :: 5 - Production/Stable
Classifier: Intended Audience :: Developers
Classifier: Intended Audience :: Science/Research
Classifier: Topic :: Scientific/Engineering :: Artificial Intelligence
Classifier: Topic :: Text Processing :: Linguistic
Classifier: License :: OSI Approved :: BSD License
Requires-Python: >=3.8
License-File: LICENSE
